scicoda/__init__.py
scicoda/atom.py
scicoda/data.py
scicoda/exception.py
scicoda/pdb.py
scicoda/data/atom/autodock_atom_types.yaml
scicoda/data/atom/periodic_table.parquet
scicoda/data/atom/symbols.yaml
scicoda/data/atom/van_der_waals_radii.yaml
scicoda/data/pdb/ccd-chem_comp.parquet
scicoda/data/pdb/ccd-chem_comp_atom.parquet
scicoda/data/pdb/ccd-chem_comp_bond.parquet
scicoda/data/pdb/ccd-pdbx_chem_comp_atom_related.parquet
scicoda/data/pdb/ccd-pdbx_chem_comp_audit.parquet
scicoda/data/pdb/ccd-pdbx_chem_comp_descriptor.parquet
scicoda/data/pdb/ccd-pdbx_chem_comp_feature.parquet
scicoda/data/pdb/ccd-pdbx_chem_comp_identifier.parquet
scicoda/data/pdb/ccd-pdbx_chem_comp_pcm.parquet
scicoda/data/pdb/ccd-pdbx_chem_comp_related.parquet
scicoda/data/pdb/ccd-pdbx_chem_comp_synonyms.parquet
scicoda/update/__init__.py
scicoda/update/df_overlap.py
scicoda/update/io.py
scicoda/update/pdb.py
scicoda/update/pubchem.py
scicoda-0.2.3.dist-info/METADATA
scicoda-0.2.3.dist-info/WHEEL
scicoda-0.2.3.dist-info/top_level.txt
scicoda-0.2.3.dist-info/RECORD
