Metadata-Version: 2.4
Name: SciCoDa
Version: 0.2.3
Requires-Python: >=3.10
Requires-Dist: pkgdata<0.2,>=0.1
Requires-Dist: pyserials<0.2,>=0.1
Requires-Dist: pandas
Requires-Dist: pyarrow
Provides-Extra: update
Requires-Dist: pandas; extra == "update"
Requires-Dist: pyarrow; extra == "update"
Requires-Dist: sciapi; extra == "update"
Requires-Dist: openmm; extra == "update"
